{
  "candidateId": 2366596,
  "apps": [
    "mail.google.com",
    "x.com"
  ],
  "detailedScreenDescription": [
    {
      "capturedAt": "2024-06-11T22:08:31Z",
      "desktop": {
        "uiElements": [
          {
            "elementType": "taskbar",
            "details": "icons for Minimize, Pending, Magic Academy, Budget, X, Google Chrome, and other unidentified applications. Also includes system clock showing '16:08' and date '11 Jun 2024'.",
            "position": "bottom"
          }
        ],
        "applications": [
          {
            "appName": "Google Chrome",
            "windows": [
              {
                "title": "Chief AI Officer on X: \"5 new market maps in AI 1. AI code generation tools from Greylock https://t.co/9yOnKkH1AA\" / X - Google Chrome",
                "url": "https://x.com/chiefaiofficer/status/1799766",
                "position": "center",
                "isActive": true,
                "uiElements": {
                  "details": "UI includes back, forward, refresh buttons, address bar, tabs, and profile icon."
                },
                "content": [
                  {
                    "title": "Enhancing Engineer Workflows",
                    "layoutDescription": "List of categories and companies",
                    "visibleText": "Enhancing Engineer Workflows\n\nWRITING CODE\nbuilder.io\nCodeComplete\ncodeium\nCodeStor CODE\nBlinqO\ncodeium\ncodium*\nMeticulous\nmomen WOLF\nventrilo.Ai\n\nPRODUCTION\nBito\ncodeium\nC REVIEW\nDetail\nDosu\ngrit*\nSECOND\nSweep AI\n\nMAINTENANCE\nkomment\nmutable.ai\n\nCODE SEARCH\ncodeium\ncodium*\nCursor\nSourcegraph"
                  }
                ]
              }
            ]
          }
        ]
      }
    }
  ],
  "activitySummary": [
    "The user is actively engaged in research activities. They are browsing a webpage on X (formerly Twitter) that discusses various AI tools for enhancing engineer workflows. The page lists different categories such as writing code, testing code, code review, maintenance, documentation, and code search, along with the corresponding AI tools available for each category. This indicates that the user is likely exploring or comparing different AI tools for potential use in their projects.",
    "The user is also checking their email on Google Mail. The presence of multiple tabs related to Google Mail suggests that the user is managing their inbox, possibly reading and responding to emails. This activity is crucial for communication and staying updated with team members or project-related information.",
    "The user has multiple tabs open in their web browser, including tabs for 'Core', 'DevFactory', 'Magic Academy', and 'Budget'. While the specific content of these tabs is not visible, it indicates that the user is multitasking and possibly working on different aspects of their projects or tasks simultaneously."
  ],
  "aiUseSummary": "There is no direct evidence of AI tools being used in the provided screenshots. The user is primarily engaged in research and email activities. However, the research involves exploring various AI tools for enhancing engineer workflows, which suggests an interest in leveraging AI for future tasks.",
  "activities": [
    "RESEARCH",
    "EMAIL"
  ],
  "workTypes": [],
  "programmingLanguages": [],
  "toolTypes": [
    "WEB_BROWSER"
  ],
  "aiTools": [],
  "usingAi": false,
  "mostRelevantActivity": "RESEARCH",
  "doubts": [],
  "confidenceScore": 90,
  "events": [
    {
      "keyboard": 26,
      "mouse": 18,
      "date": "2024-06-11T22:00:49Z",
      "windowTitle": "DevFactory Mail - Google Chrome",
      "processName": "mail.google.com",
      "visitingUrl": "mail.google.com/mail/u/0/#chat/space/AAAADn3omDE",
      "keylog": "",
      "cpuUsage": 0,
      "memUsage": 0,
      "mobile": false,
      "idle": false
    },
    {
      "keyboard": 39,
      "mouse": 26,
      "date": "2024-06-11T22:01:49Z",
      "windowTitle": "DevFactory Mail - Google Chrome",
      "processName": "mail.google.com",
      "visitingUrl": "mail.google.com/mail/u/0/#chat/space/AAAABIa6LFM",
      "keylog": "",
      "cpuUsage": 0,
      "memUsage": 0,
      "mobile": false,
      "idle": false
    },
    {
      "keyboard": 0,
      "mouse": 14,
      "date": "2024-06-11T22:02:49Z",
      "windowTitle": "DevFactory Mail - Google Chrome",
      "processName": "mail.google.com",
      "visitingUrl": "mail.google.com/mail/u/0/#chat/space/AAAAF7cTeHM",
      "keylog": "",
      "cpuUsage": 0,
      "memUsage": 0,
      "mobile": false,
      "idle": false
    },
    {
      "keyboard": 2,
      "mouse": 29,
      "date": "2024-06-11T22:03:49Z",
      "windowTitle": "Re: @gt.school / @learnwith.ai email domains - isaac.squires@trilogy.com - DevFactory Mail - Google Chrome",
      "processName": "mail.google.com",
      "visitingUrl": "mail.google.com/mail/u/0/#inbox/FMfcgzQVwngXKKHSGGcDxxpSTZNBpxGV",
      "keylog": "",
      "cpuUsage": 0,
      "memUsage": 0,
      "mobile": false,
      "idle": false
    },
    {
      "keyboard": 0,
      "mouse": 12,
      "date": "2024-06-11T22:04:49Z",
      "windowTitle": "Fwd: Q3'24 Budget Packs - Samy's group - isaac.squires@trilogy.com - DevFactory Mail - Google Chrome",
      "processName": "mail.google.com",
      "visitingUrl": "mail.google.com/mail/u/0/#inbox/FMfcgzGxTPHJkggMWlfFRLFLCHrddtFC",
      "keylog": "",
      "cpuUsage": 0,
      "memUsage": 0,
      "mobile": false,
      "idle": false
    },
    {
      "keyboard": 0,
      "mouse": 20,
      "date": "2024-06-11T22:05:48Z",
      "windowTitle": "Inbox (6) - isaac.squires@trilogy.com - DevFactory Mail - Google Chrome",
      "processName": "mail.google.com",
      "visitingUrl": "mail.google.com/mail/u/0/#inbox",
      "keylog": "",
      "cpuUsage": 0,
      "memUsage": 0,
      "mobile": false,
      "idle": false
    },
    {
      "keyboard": 0,
      "mouse": 3,
      "date": "2024-06-11T22:06:48Z",
      "windowTitle": "(9) Chief AI Officer on X: \"5 new market maps in AI 1. AI code generation tools from Greylock https://t.co/9yOnKkH1AA\" / X - Google Chrome",
      "processName": "x.com",
      "visitingUrl": "x.com/chiefaioffice/status/1799766662746398851/photo/1",
      "keylog": "",
      "cpuUsage": 0,
      "memUsage": 0,
      "mobile": false,
      "idle": false
    },
    {
      "keyboard": 0,
      "mouse": 0,
      "date": "2024-06-11T22:07:48Z",
      "windowTitle": "(9) Chief AI Officer on X: \"5 new market maps in AI 1. AI code generation tools from Greylock https://t.co/9yOnKkH1AA\" / X - Google Chrome",
      "processName": "x.com",
      "visitingUrl": "x.com/chiefaioffice/status/1799766662746398851/photo/1",
      "keylog": "",
      "cpuUsage": 0,
      "memUsage": 0,
      "mobile": false,
      "idle": true
    },
    {
      "keyboard": 0,
      "mouse": 0,
      "date": "2024-06-11T22:08:48Z",
      "windowTitle": "(9) Chief AI Officer on X: \"5 new market maps in AI 1. AI code generation tools from Greylock https://t.co/9yOnKkH1AA\" / X - Google Chrome",
      "processName": "x.com",
      "visitingUrl": "x.com/chiefaioffice/status/1799766662746398851/photo/1",
      "keylog": "",
      "cpuUsage": 0,
      "memUsage": 0,
      "mobile": false,
      "idle": true
    },
    {
      "keyboard": 0,
      "mouse": 0,
      "date": "2024-06-11T22:09:48Z",
      "windowTitle": "(9) Chief AI Officer on X: \"5 new market maps in AI 1. AI code generation tools from Greylock https://t.co/9yOnKkH1AA\" / X - Google Chrome",
      "processName": "x.com",
      "visitingUrl": "x.com/chiefaioffice/status/1799766662746398851/photo/1",
      "keylog": "",
      "cpuUsage": 0,
      "memUsage": 0,
      "mobile": false,
      "idle": true
    }
  ],
  "timestamp": "2024-06-11T22:00:00Z"
}