{
  "candidateId": 20104,
  "apps": [
    "chrome"
  ],
  "detailedScreenDescription": [
    {
      "capturedAt": "2024-06-04T11:42:43Z",
      "desktop": {
        "uiElements": [
          {
            "elementType": "taskbar",
            "details": "icons for Google Chrome, File Explorer, Microsoft Edge, and other unidentified applications. System tray includes network, sound, and clock (2:42 PM, 6/4/2024)",
            "position": "bottom"
          }
        ],
        "applications": [
          {
            "appName": "Google Chrome",
            "windows": [
              {
                "title": "Jive Upgrade - Google Docs",
                "url": "https://docs.google.com/document/d/1",
                "position": "left half of the screen",
                "isActive": true,
                "uiElements": {
                  "details": "Menu bar with File, Edit, View, Insert, Format, Tools, Extensions, Help. Toolbar with undo, redo, print, spelling and grammar check, zoom level, styles, and formatting options."
                },
                "content": [
                  {
                    "title": "Jive Upgrade",
                    "layoutDescription": "Document layout with text and tables",
                    "visibleText": "Jive Upgrade\n\nSlot #2\n\nCustomer engagement/rollout - BA2: IgniteTech : Jive - Jive AI Copilot\n\nProgress Week 22\n- Switched our strategy to reach out to all Cloud customers (write-up) and contacted 90 users at 84 companies in an attempt to enlarge our pool of customers we can work with:\n - Aside from the standard contacts, we also include all users who have been active on Zendesk (list)\n- Create How-to-Summarize videos designed to get customer attention: Get Answers with Copilot\n- Written Handbooks to share with Libro, CC, and P2S, so they can start asking questions instead of keywords.\n- A total of 134 usages happened between 27.05-31.05\n - Libro: 106 usages / CC: 25 usages\n - Down-votes: 3 / Up-votes: 2\n\nMetrics/KPIs\n\nOutreach efforts\n\nSegment 1 (Initial Interest)\nSegment 2 (Compliance)\nSegment 3 (High ARR, Avg. Use)\n\nCustomers in segment\n\nReached\n- Interested\n- Declined\n\nEnabled"
                  }
                ]
              },
              {
                "title": "Meet - aqm-tpng-aqq",
                "url": "https://meet.google.com/aqm-",
                "position": "right half of the screen",
                "isActive": false,
                "uiElements": {
                  "details": "Video conference controls including microphone, camera, and presentation options."
                },
                "content": [
                  {
                    "title": "Google Meet",
                    "layoutDescription": "Video call interface",
                    "visibleText": "Dragos Nuta (You, presenting)\nStop presenting\n\nGeorge Dita\n\n2 others\n\nThey wanted prompts because they were mostly not aware of their Copilot capabilities. That was the discussion's result from last week. I sent it to P2S as"
                  }
                ]
              }
            ]
          }
        ]
      }
    },
    {
      "capturedAt": "2024-06-04T11:45:10Z",
      "desktop": {
        "uiElements": [
          {
            "elementType": "taskbar",
            "details": "icons for Google Chrome, File Explorer, Microsoft Edge, and other unidentified applications. System tray includes network, sound, and clock (2:45 PM, 6/4/2024)",
            "position": "bottom"
          }
        ],
        "applications": [
          {
            "appName": "Google Chrome",
            "windows": [
              {
                "title": "Jive Upgrade - Google Docs",
                "url": "https://docs.google.com/document/d/1",
                "position": "maximized",
                "isActive": true,
                "uiElements": {
                  "details": "Menu bar with options for File, Edit, View, Insert, Format, Tools, Extensions, Help. Toolbar with undo, redo, print, spelling and grammar check, styles, zoom, and other editing options. Right sidebar with document outline and chat panel."
                },
                "content": [
                  {
                    "title": "Jive Upgrade",
                    "layoutDescription": "Text document layout",
                    "visibleText": "Slot #2\n\nCustomer engagement/rollout - BA2: IgniteTech : Jive - Jive AI Copilot\n\nProgress Week 22\n- Switched our strategy to reach out to all Cloud customers (write-up) and contacted 90 users at 84 companies in an attempt to enlarge our pool of customers we can work with:\n - Aside from the standard contacts, we also include all users who have been active on Zendesk (list)\n- Create How-to-Summarize videos designed to get customer attention: Get Answers with Copilot\n- Created a handbook with valuable customer use-cases and examples, educating customers on how to properly use the L - shared with Libro, CCF, and P25, so they can start asking questions instead of keywords.\n- A total of 1340 uses happened between 27-05-31.05\n - Libro: 106 usages / CCF: 23 usages\n - Down-votes: 3 / Up-votes: 22"
                  }
                ]
              }
            ]
          }
        ]
      }
    },
    {
      "capturedAt": "2024-06-04T11:49:21Z",
      "desktop": {
        "uiElements": [
          {
            "elementType": "taskbar",
            "details": "icons for Chrome, File Explorer, Microsoft Edge, and other unidentified applications. System tray includes notifications, sound, network, and clock displaying '2:49 PM 6/4/2024'",
            "position": "bottom"
          }
        ],
        "applications": [
          {
            "appName": "Chrome",
            "windows": [
              {
                "title": "Jive Upgrade - Google Docs",
                "url": "https://docs.google.com/document/d/1",
                "position": "center",
                "isActive": true,
                "uiElements": {
                  "details": "Menu bar with File, Edit, View, Insert, Format, Tools, Extensions, Help. Toolbar with undo, redo, print, spelling and grammar check, zoom settings, styles, and formatting options. Right sidebar with document outline and Google Chat integration."
                },
                "content": [
                  {
                    "title": "Jive Upgrade",
                    "layoutDescription": "Text document layout",
                    "visibleText": "Progress Week 22\nSwitched our strategy to reach out to all Cloud customers (write-up) and contacted 90 users at 84 companies in an attempt to enlarge our pool of customers we can work with:\nAside from the standard contacts, we also include all users who have been active on Zendesk (list)\nCreate two how-to videos designed to get customer attention: Get Answers with Copilot and How-to-Summarize\nCreated a handbook with valuable customer use-cases and examples, educating customers on how to properly use the Copilot - shared with Libro, CCF, and P25\nThere were 134 conversations between 27-05 and 31-05\nLibro: 106 and CCF: 23, with 3 down-votes and 2 up-votes.\n\nMetrics/KPIs\nOutreach efforts\nSegment 1 (Initial Interest)\nSegment 2 (Compliance concerns)\nSegment 3 (All other customers)\nCustomers in segment\nReached\n- Interested\n- Declined\nEnabled\nActively using it\nJive Cloud Copilot - Outreach tracker\nTotal Enabled Companies: 7\nAdoption\nMarch 2024\nApril 2024\nMay 2024\nTotal Usage (conversations)\n105\n2288\n1573\nUp Votes (%)\n16.67\n31.96\n44.23\nDown Votes (%)\n83.33\n68.04\n55.77\nMIP Week 22\nCustomers are not enabling Copilot on their own.\nPlan Week 23\nFollow up on e-mail trackers."
                  }
                ]
              }
            ]
          }
        ]
      }
    }
  ],
  "activitySummary": [
    "The user is actively engaged in a Google Docs document titled 'Jive Upgrade'. The document contains detailed information about customer engagement and rollout strategies for the Jive AI Copilot. The user is editing and updating the document, which includes progress updates, metrics, and KPIs. The user is also participating in a Google Meet video conference, where they are presenting the document to other team members. The conversation in the chat sidebar indicates discussions about customer usage and feedback on the Jive AI Copilot.",
    "The user continues to work on the 'Jive Upgrade' document in Google Docs. They are making edits and updates to the content, specifically focusing on the progress and metrics sections. The chat sidebar shows ongoing discussions with team members about customer engagement strategies and the effectiveness of the Jive AI Copilot. The user is also sharing their screen in the Google Meet session, indicating active collaboration and presentation of the document to the team.",
    "The user is finalizing updates to the 'Jive Upgrade' document in Google Docs. They are ensuring that all progress updates, metrics, and KPIs are accurately reflected in the document. The chat sidebar shows continued discussions with team members about customer feedback and potential improvements to the Jive AI Copilot. The user is still sharing their screen in the Google Meet session, indicating that the presentation and discussion are ongoing."
  ],
  "aiUseSummary": "There is no evidence of AI tools being used in the provided screenshots. The user is primarily engaged in editing a Google Docs document and participating in a Google Meet video conference. There are no visible interactions with AI chat interfaces or AI-driven tools in the screenshots.",
  "activities": [
    "READING_SPEC",
    "WRITING_SPEC",
    "MEETING",
    "CHATTING_WITH_TEAM"
  ],
  "workTypes": [],
  "programmingLanguages": [],
  "toolTypes": [
    "DOCUMENT_VIEWER_OR_EDITOR",
    "WEB_BROWSER"
  ],
  "aiTools": [],
  "usingAi": false,
  "mostRelevantActivity": "WRITING_SPEC",
  "doubts": [],
  "confidenceScore": 95,
  "events": [
    {
      "keyboard": 0,
      "mouse": 0,
      "date": "2024-06-04T11:40:09Z",
      "windowTitle": "meet.google.com is sharing a window.",
      "processName": "chrome",
      "visitingUrl": "",
      "keylog": "",
      "cpuUsage": 0,
      "memUsage": 0,
      "mobile": false,
      "idle": true
    },
    {
      "keyboard": 0,
      "mouse": 0,
      "date": "2024-06-04T11:41:09Z",
      "windowTitle": "meet.google.com is sharing a window.",
      "processName": "chrome",
      "visitingUrl": "",
      "keylog": "",
      "cpuUsage": 0,
      "memUsage": 0,
      "mobile": false,
      "idle": true
    },
    {
      "keyboard": 4,
      "mouse": 7,
      "date": "2024-06-04T11:42:09Z",
      "windowTitle": "meet.google.com is sharing a window.",
      "processName": "chrome",
      "visitingUrl": "",
      "keylog": "",
      "cpuUsage": 0,
      "memUsage": 0,
      "mobile": false,
      "idle": false
    },
    {
      "keyboard": 121,
      "mouse": 10,
      "date": "2024-06-04T11:43:09Z",
      "windowTitle": "meet.google.com is sharing a window.",
      "processName": "chrome",
      "visitingUrl": "",
      "keylog": "",
      "cpuUsage": 0,
      "memUsage": 0,
      "mobile": false,
      "idle": false
    },
    {
      "keyboard": 162,
      "mouse": 1,
      "date": "2024-06-04T11:44:09Z",
      "windowTitle": "meet.google.com is sharing a window.",
      "processName": "chrome",
      "visitingUrl": "",
      "keylog": "",
      "cpuUsage": 0,
      "memUsage": 0,
      "mobile": false,
      "idle": false
    },
    {
      "keyboard": 181,
      "mouse": 3,
      "date": "2024-06-04T11:45:09Z",
      "windowTitle": "meet.google.com is sharing a window.",
      "processName": "chrome",
      "visitingUrl": "",
      "keylog": "",
      "cpuUsage": 0,
      "memUsage": 0,
      "mobile": false,
      "idle": false
    },
    {
      "keyboard": 119,
      "mouse": 0,
      "date": "2024-06-04T11:46:09Z",
      "windowTitle": "meet.google.com is sharing a window.",
      "processName": "chrome",
      "visitingUrl": "",
      "keylog": "",
      "cpuUsage": 0,
      "memUsage": 0,
      "mobile": false,
      "idle": false
    },
    {
      "keyboard": 101,
      "mouse": 10,
      "date": "2024-06-04T11:47:09Z",
      "windowTitle": "meet.google.com is sharing a window.",
      "processName": "chrome",
      "visitingUrl": "",
      "keylog": "",
      "cpuUsage": 0,
      "memUsage": 0,
      "mobile": false,
      "idle": false
    },
    {
      "keyboard": 30,
      "mouse": 33,
      "date": "2024-06-04T11:48:09Z",
      "windowTitle": "meet.google.com is sharing a window.",
      "processName": "chrome",
      "visitingUrl": "",
      "keylog": "",
      "cpuUsage": 0,
      "memUsage": 0,
      "mobile": false,
      "idle": false
    },
    {
      "keyboard": 11,
      "mouse": 28,
      "date": "2024-06-04T11:49:09Z",
      "windowTitle": "meet.google.com is sharing a window.",
      "processName": "chrome",
      "visitingUrl": "",
      "keylog": "",
      "cpuUsage": 0,
      "memUsage": 0,
      "mobile": false,
      "idle": false
    }
  ],
  "timestamp": "2024-06-04T11:40:00Z"
}